data_detective_airflow/__init__.py
data_detective_airflow/constants.py
data_detective_airflow/dag_generator/__init__.py
data_detective_airflow/dag_generator/dags/__init__.py
data_detective_airflow/dag_generator/dags/python_dag.py
data_detective_airflow/dag_generator/dags/tdag.py
data_detective_airflow/dag_generator/dags/yaml_dag.py
data_detective_airflow/dag_generator/generator.py
data_detective_airflow/dag_generator/results/__init__.py
data_detective_airflow/dag_generator/results/base_result.py
data_detective_airflow/dag_generator/results/pg_result.py
data_detective_airflow/dag_generator/results/pickle_result.py
data_detective_airflow/dag_generator/works/__init__.py
data_detective_airflow/dag_generator/works/base_db_work.py
data_detective_airflow/dag_generator/works/base_file_work.py
data_detective_airflow/dag_generator/works/base_work.py
data_detective_airflow/dag_generator/works/file_work.py
data_detective_airflow/dag_generator/works/pg_work.py
data_detective_airflow/dag_generator/works/s3_work.py
data_detective_airflow/dag_generator/works/sftp_work.py
data_detective_airflow/operators/__init__.py
data_detective_airflow/operators/extractors/__init__.py
data_detective_airflow/operators/extractors/db_dump.py
data_detective_airflow/operators/extractors/python_dump.py
data_detective_airflow/operators/extractors/request_dump.py
data_detective_airflow/operators/extractors/s3_dump.py
data_detective_airflow/operators/extractors/s3_list_bucket.py
data_detective_airflow/operators/extractors/tsftpoperator.py
data_detective_airflow/operators/sinks/__init__.py
data_detective_airflow/operators/sinks/pg_loader.py
data_detective_airflow/operators/sinks/pg_scd1.py
data_detective_airflow/operators/sinks/pg_scd1_df_update_insert.py
data_detective_airflow/operators/sinks/pg_single_target_loader.py
data_detective_airflow/operators/sinks/pg_single_target_utils.py
data_detective_airflow/operators/sinks/s3_delete.py
data_detective_airflow/operators/sinks/s3_load.py
data_detective_airflow-2.2.0.dist-info/WHEEL
data_detective_airflow-2.2.0.dist-info/METADATA
data_detective_airflow-2.2.0.dist-info/RECORD
